dasha/__init__.py
dasha/utils.py
dasha-1.0.0.dist-info/DESCRIPTION.rst
dasha-1.0.0.dist-info/METADATA
dasha-1.0.0.dist-info/RECORD
dasha-1.0.0.dist-info/WHEEL
dasha-1.0.0.dist-info/metadata.json
dasha-1.0.0.dist-info/top_level.txt
