Metadata-Version: 2.0
Name: dasha
Version: 1.0.0
Summary: find word or words in text
Home-page: https://github.com/serbernar/dasha
Author: Sergey Berebko
Author-email: serbernar1@gmail.com
License: MIT
Download-URL: https://github.com/serbernar/dasha/archive/master.zip
Platform: UNKNOWN
Classifier: License :: OSI Approved :: MIT License
Classifier: Programming Language :: Python :: 3.4
Classifier: Programming Language :: Python :: 3.5
Classifier: Programming Language :: Python :: 3.6
